cis_checks_5/__init__.py
cis_checks_5/iam_control_1.py
cis_checks_5/logging_control_2.py
cis_checks_5/monitoring_control_3.py
cis_checks_5/networking_control_4.py
cis_checks_5/security_control_5.py
cis_checks_5/utils.py
cis_checks_5-0.0.6.dist-info/METADATA
cis_checks_5-0.0.6.dist-info/WHEEL
cis_checks_5-0.0.6.dist-info/top_level.txt
cis_checks_5-0.0.6.dist-info/RECORD
